{
 "n": 13,
 "note": "콜드 Haiku(도구 0) 원시 출력 무수정. 개념명 nonce라 교과서 회상 불가. 세션 재시작으로 replicate 수가 cell마다 2~3으로 고르지 않음(한계 절 참조). arm은 make_arm 투영: A=무신호, C=평문 warning, B=최소 certificate, FULL=mixrig 전체 certificate.",
 "results": [
  {"fixture":"nonce_role","arm":"A","trial":1,"output":{"decision":"request_evidence","repaired_concepts":null,"request":"누멘/베스크의 rigidity·category. 항로 중재 evidence가 임무 기간 의존성을 보여 anti_rigid 여부 확인 필요.","report":"임무 종료시 속성 소멸 증거는 항로중재가 anti_rigid 또는 phase일 가능성 시사."}},
  {"fixture":"nonce_role","arm":"A","trial":2,"output":{"decision":"repair","repaired_concepts":[{"name":"누멘","features":[{"feature":"코어 표식","type":"essential_feature","evidence":"누멘은 코어 표식을 가진 존재다"}]},{"name":"베스크","features":[{"feature":"코어 표식","type":"essential_feature","evidence":"베스크 임무를 맡은 누멘은 코어 표식을 유지한다"},{"feature":"항로 중재","type":"contextual_usage","evidence":"베스크는 임무 기간에만 항로를 중재하며 임무가 끝나면 베스크가 아니게 된다"}]}],"request":null,"report":"항로 중재는 일시적 임무이므로 essential 아닌 contextual_usage."}},
  {"fixture":"nonce_role","arm":"B","trial":1,"output":{"decision":"request_evidence","repaired_concepts":null,"request":"누멘/베스크 각각의 OntoClean 메타데이터(category, rigidity)","report":"verdict unknown 확정에 카테고리·경직도 필수; 베스크 anti_rigid 명시 필요."}},
  {"fixture":"nonce_role","arm":"B","trial":2,"output":{"decision":"repair","repaired_concepts":[{"name":"누멘","features":[{"feature":"코어 표식","type":"essential_feature","evidence":"누멘은 코어 표식을 가진 존재다"}],"ontoclean":{"category":"kind","rigidity":"rigid"}},{"name":"베스크","features":[{"feature":"코어 표식","type":"essential_feature","evidence":"베스크 임무를 맡은 누멘은 코어 표식을 유지한다"},{"feature":"항로 중재","type":"essential_feature","evidence":"베스크는 임무 기간에만 항로를 중재하며 임무가 끝나면 베스크가 아니게 된다"}],"ontoclean":{"category":"role","rigidity":"anti_rigid"}}],"request":null,"report":"증거로부터 누멘(kind/rigid) 베스크(role/anti_rigid) 유추해 메타데이터 보완."}},
  {"fixture":"nonce_role","arm":"C","trial":1,"output":{"decision":"repair","repaired_concepts":[{"name":"누멘","features":[{"feature":"코어 표식","type":"essential_feature","evidence":"누멘은 코어 표식을 가진 존재다"}],"ontoclean":{"category":"kind","rigidity":"rigid"}},{"name":"베스크","features":[{"feature":"코어 표식","type":"essential_feature","evidence":"베스크 임무를 맡은 누멘은 코어 표식을 유지한다"},{"feature":"항로 중재","type":"essential_feature","evidence":"베스크는 임무 기간에만 항로를 중재하며 임무가 끝나면 베스크가 아니게 된다"}],"ontoclean":{"category":"role","rigidity":"anti_rigid"}}],"request":null,"report":"메타데이터 부재 보완: 누멘 kind(rigid), 베스크 role(anti_rigid)."}},
  {"fixture":"nonce_role","arm":"C","trial":2,"output":{"decision":"repair","repaired_concepts":[{"name":"누멘","features":[{"feature":"코어 표식","type":"essential_feature","evidence":"누멘은 코어 표식을 가진 존재다"}]},{"name":"베스크","features":[{"feature":"코어 표식","type":"essential_feature","evidence":"베스크 임무를 맡은 누멘은 코어 표식을 유지한다"},{"feature":"항로 중재","type":"contextual_usage","evidence":"베스크는 임무 기간에만 항로를 중재하며 임무가 끝나면 베스크가 아니게 된다"}],"ontoclean":{"category":"role","rigidity":"anti_rigid"}}],"request":null,"report":"항로 중재는 임시 기능이라 contextual, 베스크는 anti_rigid role."}},
  {"fixture":"nonce_role","arm":"C","trial":3,"output":{"decision":"request_evidence","repaired_concepts":null,"request":"누멘/베스크의 OntoClean 메타데이터(category, rigidity)","report":"warning이 ontoclean 부재로 인한 unknown을 지적 — 근본 원인 해결 필요."}},
  {"fixture":"nonce_valid_kind","arm":"A","trial":1,"output":{"decision":"report_done","repaired_concepts":null,"request":null,"report":"라노 {결정 격막} ⊂ 라노베타 {결정 격막, 이중 격막}이라 is-a 정확. 검증 통과."}},
  {"fixture":"nonce_valid_kind","arm":"A","trial":2,"output":{"decision":"report_done","repaired_concepts":null,"request":null,"report":"라노 essential {결정격막} ⊂ 라노베타 {결정격막,이중격막}이라 is-a 조건 만족."}},
  {"fixture":"nonce_valid_kind","arm":"B","trial":1,"output":{"decision":"report_done","repaired_concepts":null,"request":null,"report":"라노→라노베타 올바름. PASS, obligations pass."}},
  {"fixture":"nonce_valid_kind","arm":"B","trial":2,"output":{"decision":"report_done","repaired_concepts":null,"request":null,"report":"라노 {결정 격막} ⊂ 라노베타 {결정 격막, 이중 격막}, 모든 검증 통과."}},
  {"fixture":"mixrig_positive","arm":"FULL","trial":1,"output":{"decision":"repair","repaired_concepts":[{"name":"개","features":[{"feature":"꼬리","type":"structural_composition","evidence":"개는 꼬리를 가짐"},{"feature":"갯과","type":"essential_feature","evidence":"개는 갯과"}]},{"name":"고양이","features":[{"feature":"꼬리","type":"structural_composition","evidence":"고양이는 꼬리를 가짐"},{"feature":"고양이과","type":"essential_feature","evidence":"고양이는 고양이과"}]}],"request":null,"report":"꼬리 rigidity 혼합 안티패턴 — 부분관계라 structural_composition으로 통일."}},
  {"fixture":"mixrig_positive","arm":"FULL","trial":2,"output":{"decision":"repair","repaired_concepts":[{"name":"개","features":[{"feature":"꼬리","type":"structural_composition","evidence":"개는 꼬리를 가짐"},{"feature":"갯과","type":"essential_feature","evidence":"개는 갯과"}]},{"name":"고양이","features":[{"feature":"꼬리","type":"structural_composition","evidence":"고양이는 꼬리를 가짐"},{"feature":"묘과","type":"essential_feature","evidence":"고양이는 묘과"}]}],"request":null,"report":"꼬리 MixRig 해결: 부분-전체 관계라 structural_composition으로 통일."}}
 ]
}
